{
  "id": "family",
  "name": "Family",
  "nameZh": "е®¶дәә",
  "emoji": "рҹ‘ЁвҖҚрҹ‘©вҖҚрҹ‘Ұ",
  "color": "#F472B6",
  "words": [
    {
      "id": "mom",
      "english": "mom",
      "chinese": "еҰҲеҰҲ",
      "pinyin": "mДҒma",
      "image": "/images/family/mom.png"
    },
    {
      "id": "dad",
      "english": "dad",
      "chinese": "зҲёзҲё",
      "pinyin": "bГ ba",
      "image": "/images/family/dad.png"
    },
    {
      "id": "grandma",
      "english": "grandma",
      "chinese": "еҘ¶еҘ¶",
      "pinyin": "nЗҺinai",
      "image": "/images/family/grandma.png"
    },
    {
      "id": "grandpa",
      "english": "grandpa",
      "chinese": "зҲ·зҲ·",
      "pinyin": "yГ©ye",
      "image": "/images/family/grandpa.png"
    },
    {
      "id": "brother",
      "english": "brother",
      "chinese": "е“Ҙе“Ҙ",
      "pinyin": "gД“ge",
      "image": "/images/family/brother.png"
    },
    {
      "id": "sister",
      "english": "sister",
      "chinese": "е§җе§җ",
      "pinyin": "jiДӣjie",
      "image": "/images/family/sister.png"
    },
    {
      "id": "baby",
      "english": "baby",
      "chinese": "е®қе®қ",
      "pinyin": "bЗҺobao",
      "image": "/images/family/baby.png"
    }
  ]
}
